meltingpot/__init__.py
meltingpot/ga.py
meltingpot/penalties.py
meltingpot-1.0.0.dist-info/DESCRIPTION.rst
meltingpot-1.0.0.dist-info/METADATA
meltingpot-1.0.0.dist-info/RECORD
meltingpot-1.0.0.dist-info/WHEEL
meltingpot-1.0.0.dist-info/metadata.json
meltingpot-1.0.0.dist-info/top_level.txt
