Metadata-Version: 2.0
Name: meltingpot
Version: 1.0.0
Summary: A lightweight genetic algorithm module for optimization problems
Home-page: https://github.com/acapitanelli/meltingpot
Author: andrea capitanelli
Author-email: andrea.capitanelli@gmail.com
Maintainer: andrea capitanelli
Maintainer-email: andrea.capitanelli@gmail.com
License: MIT
Keywords: optimization genetic algorithm constraints
Platform: UNKNOWN
Classifier: Development Status :: 3 - Alpha
Classifier: License :: OSI Approved :: MIT License
Classifier: Programming Language :: Python :: 3
Classifier: Topic :: Scientific/Engineering :: Artificial Intelligence
Requires-Dist: numpy
